{
  "taskId": 107,
  "name": "Level 5 Simple",
  "difficulty": 2.9,
  "type": "set",
  "stepsNum": 3,
  "time": 120,
  "originalExpression": "A|(B\\A)",
  "finalExpression": "A|B",
  "allSubstitutions":[
    {"left":"A|(B|C)","right":"A|B|C"},
    {"left":"A|B|C","right":"A|(B|C)"},
    {"left":"A&(B&C)","right":"A&B&C"},
    {"left":"A&B&C","right":"A&(B&C)"},
    {"left":"A&(B&C)","right":"(A&B)&C"},
    {"left":"(A|B)|C","right":"A|B|C"},
    {"left":"A|B|C","right":"(A|B)|C"},
    {"left":"(A&B)&C","right":"A&B&C"},
    {"left":"A&B&C","right":"(A&B)&C"},
    {"left":"A|(B&C)","right":"(A|B)&(A|C)"},
    {"left":"(A|B)&(A|C)","right":"A|(B&C)"},
    {"left":"A&(B|C)","right":"(A&B)|(A&C)"},
    {"left":"(A&B)|(A&C)","right":"A&(B|C)"},
    {"left":"!(A&B)","right":"!A|!B"},
    {"left":"!(A&B)","right":"!(B&A)"},
    {"left":"!A|!B","right":"!(A&B)"},
    {"left":"!(A|B)","right":"!A&!B"},
    {"left":"!(A|B)","right":"!B&!A"},
    {"left":"!(A|B)","right":"!(B|A)"},
    {"left":"!A&!B","right":"!(A|B)"},
    {"left":"!A|B","right":"A->B"},
    {"left":"A->B","right":"!A|B"},
    {"left":"A&!B","right":"A\\B"},
    {"left":"A\\B","right":"A&!B"},
    {"left":"!(!A)","right":"A"},
    {"left":"A","right":"!(!A)"},
    {"left":"A&(A|B)","right":"A"},
    {"left":"A","right":"A&(A|B)"},
    {"left":"A|A","right":"A"},
    {"left":"A","right":"A|A"},
    {"left":"A&A","right":"A"},
    {"left":"A&B","right":"B&A"},
    {"left":"A|B","right":"B|A"},
    {"left":"A","right":"A&A"},
    {"left":"(A|B)&(A|!A)","right":"A|B"},
    {"left":"A\\B","right":"!(B->A)"},
    {"left":"!(B->A)","right":"A\\B"},
    {"left":"B->A","right":"!(A\\B)"},
    {"left":"!(A\\B)","right":"B->A"}
  ]
}